rnnoise_cli/__init__.py
rnnoise_cli/commands.py
rnnoise_cli/pretty.py
rnnoise_cli/data/__init__.py
rnnoise_cli/data/librnnoise_ladspa.so
rnnoise_cli/data/license_info.txt
rnnoise_cli/pulse/__init__.py
rnnoise_cli/pulse/exceptions.py
rnnoise_cli/pulse/pulse.py
rnnoise_cli-1.0.3.dist-info/LICENSE
rnnoise_cli-1.0.3.dist-info/METADATA
rnnoise_cli-1.0.3.dist-info/WHEEL
rnnoise_cli-1.0.3.dist-info/entry_points.txt
rnnoise_cli-1.0.3.dist-info/top_level.txt
rnnoise_cli-1.0.3.dist-info/RECORD
