Metadata-Version: 2.1
Name: rnnoise-cli
Version: 1.0.3
Summary: "A CLI for werman's noise-suppression-for-voice"
Home-page: https://github.com/IniasP/rnnoise-cli
Author: Inias Peeters
Author-email: iniasp@gmail.com
License: UNKNOWN
Platform: UNKNOWN
Classifier: Programming Language :: Python :: 3
Classifier: License :: OSI Approved :: GNU General Public License v3 (GPLv3)
Classifier: Operating System :: POSIX :: Linux
Requires-Python: >=3.7
License-File: LICENSE
Requires-Dist: click (~=8.0.3)
Requires-Dist: pulsectl (~=22.1.3)
